pyresumeparser/__init__.py
pyresumeparser/_version.py
pyresumeparser/main.py
pyresumeparser-0.0.9.dist-info/METADATA
pyresumeparser-0.0.9.dist-info/WHEEL
pyresumeparser-0.0.9.dist-info/entry_points.txt
pyresumeparser-0.0.9.dist-info/top_level.txt
pyresumeparser-0.0.9.dist-info/RECORD
