Metadata-Version: 2.1
Name: pyresumeparser
Version: 0.0.9
Summary: A package for parsing resume and extracting entities.
Home-page: https://github.com/pkhan123/pyresumeparser
Author: Palash Khan
Author-email: palashkhan777@gmail.com
Classifier: Programming Language :: Python :: 3.10
Classifier: License :: OSI Approved :: MIT License
Classifier: Operating System :: OS Independent
Requires-Python: >=3.10
Requires-Dist: pdfminer.six ==20231228
Requires-Dist: spacy ==3.7.4
Requires-Dist: spacy-transformers ==1.3.5
Requires-Dist: tqdm ==4.66.4
Provides-Extra: dev
Requires-Dist: build ; extra == 'dev'
Requires-Dist: twine ; extra == 'dev'
